pythondl/__init__.py
pythondl-1.1.2.data/scripts/pydownloader
pythondl-1.1.2.dist-info/LICENSE
pythondl-1.1.2.dist-info/METADATA
pythondl-1.1.2.dist-info/WHEEL
pythondl-1.1.2.dist-info/top_level.txt
pythondl-1.1.2.dist-info/RECORD
