Metadata-Version: 2.1
Name: pythondl
Version: 1.1.2
Summary: Download YT videos using this simple tool!
Home-page: UNKNOWN
Author: Calamity34
Author-email: nick.goloushckin@ya.ru
License: MIT
Platform: UNKNOWN
Classifier: License :: OSI Approved :: MIT License
Classifier: Programming Language :: Python :: 3
Classifier: Programming Language :: Python :: 3.8
Requires-Dist: beautifulsoup4
Requires-Dist: bs4
Requires-Dist: pytube3
Requires-Dist: requests
